Workbook

Sheet Resumen por proveedor
A1: OPERACIONES ACTIVAS POR PROVEEDOR — Easy Logistics · 22-jul-2026
A2: Cuántas operaciones activas tienes con cada proveedor y en qué van, para consolidar tus llamadas. El # de operaciones se calcula solo (COUNTIF) sobre la hoja 'Detalle filtrable'. Ordenado de más a menos operaciones.
A4: Proveedor | B4: Rol principal | C4: # Operaciones | D4: Críticas | E4: Altas | F4: Contacto / nota
A5: Tri Cargo | B5: Aduana / DO | C5: =COUNTIF('Detalle filtrable'!$A:$A,$A5) -> 20 | D5: =COUNTIFS('Detalle filtrable'!$A:$A,$A5,'Detalle filtrable'!$C:$C,"CRÍTICA") -> 6 | E5: =COUNTIFS('Detalle filtrable'!$A:$A,$A5,'Detalle filtrable'!$C:$C,"ALTA") -> 12 | F5: Edison Cárdenas (comercial3), customerservice2, importaciones, Laura Sarmiento (trámites)
A6: Anker | B6: Flete / consolidación | C6: =COUNTIF('Detalle filtrable'!$A:$A,$A6) -> 11 | D6: =COUNTIFS('Detalle filtrable'!$A:$A,$A6,'Detalle filtrable'!$C:$C,"CRÍTICA") -> 5 | E6: =COUNTIFS('Detalle filtrable'!$A:$A,$A6,'Detalle filtrable'!$C:$C,"ALTA") -> 4 | F6: Andrea Segura (comercial11), Angela Castro (transportes), radicaciones1, cartera
A7: Interlogística ZF | B7: Aduana ZF Cartagena | C7: =COUNTIF('Detalle filtrable'!$A:$A,$A7) -> 5 | D7: =COUNTIFS('Detalle filtrable'!$A:$A,$A7,'Detalle filtrable'!$C:$C,"CRÍTICA") -> 1 | E7: =COUNTIFS('Detalle filtrable'!$A:$A,$A7,'Detalle filtrable'!$C:$C,"ALTA") -> 4 | F7: Stefania Torres (storres), Katherin Soler (ksoler), cartera
A8: Aggio | B8: Flete origen | C8: =COUNTIF('Detalle filtrable'!$A:$A,$A8) -> 4 | D8: =COUNTIFS('Detalle filtrable'!$A:$A,$A8,'Detalle filtrable'!$C:$C,"CRÍTICA") -> 0 | E8: =COUNTIFS('Detalle filtrable'!$A:$A,$A8,'Detalle filtrable'!$C:$C,"ALTA") -> 4 | F8: Caton Huang / Zeal Liu (overseas)
A9: Interlace | B9: Aduana (grupo) | C9: =COUNTIF('Detalle filtrable'!$A:$A,$A9) -> 3 | D9: =COUNTIFS('Detalle filtrable'!$A:$A,$A9,'Detalle filtrable'!$C:$C,"CRÍTICA") -> 2 | E9: =COUNTIFS('Detalle filtrable'!$A:$A,$A9,'Detalle filtrable'!$C:$C,"ALTA") -> 0 | F9: Aduana Grupo Interlace
A10: Andes (AndesbyApex) | B10: Flete / agente origen | C10: =COUNTIF('Detalle filtrable'!$A:$A,$A10) -> 2 | D10: =COUNTIFS('Detalle filtrable'!$A:$A,$A10,'Detalle filtrable'!$C:$C,"CRÍTICA") -> 1 | E10: =COUNTIFS('Detalle filtrable'!$A:$A,$A10,'Detalle filtrable'!$C:$C,"ALTA") -> 0 | F10: Liz Sanabria, Tania Castaño (@andesbyapex.com)
A11: Ascointer | B11: Aduana del cliente | C11: =COUNTIF('Detalle filtrable'!$A:$A,$A11) -> 2 | D11: =COUNTIFS('Detalle filtrable'!$A:$A,$A11,'Detalle filtrable'!$C:$C,"CRÍTICA") -> 0 | E11: =COUNTIFS('Detalle filtrable'!$A:$A,$A11,'Detalle filtrable'!$C:$C,"ALTA") -> 1 | F11: Samary Valencia, Auristela Atencio (despachosbun2)
A12: GL Cargo | B12: Flete / agente origen | C12: =COUNTIF('Detalle filtrable'!$A:$A,$A12) -> 2 | D12: =COUNTIFS('Detalle filtrable'!$A:$A,$A12,'Detalle filtrable'!$C:$C,"CRÍTICA") -> 0 | E12: =COUNTIFS('Detalle filtrable'!$A:$A,$A12,'Detalle filtrable'!$C:$C,"ALTA") -> 1 | F12: Jennifer Aroca, Karen Sánchez, Camilo Pita (operaciones1)
A13: HAPO Customs | B13: Aduana | C13: =COUNTIF('Detalle filtrable'!$A:$A,$A13) -> 2 | D13: =COUNTIFS('Detalle filtrable'!$A:$A,$A13,'Detalle filtrable'!$C:$C,"CRÍTICA") -> 2 | E13: =COUNTIFS('Detalle filtrable'!$A:$A,$A13,'Detalle filtrable'!$C:$C,"ALTA") -> 0 | F13: Diego Sabogal (NIT 860533331-0)
A14: MSL Corporate | B14: Aéreo / agente | C14: =COUNTIF('Detalle filtrable'!$A:$A,$A14) -> 2 | D14: =COUNTIFS('Detalle filtrable'!$A:$A,$A14,'Detalle filtrable'!$C:$C,"CRÍTICA") -> 0 | E14: =COUNTIFS('Detalle filtrable'!$A:$A,$A14,'Detalle filtrable'!$C:$C,"ALTA") -> 2 | F14: aereoimpo@mslcorporate; insales8
A15: Quick | B15: Terrestre (inland) | C15: =COUNTIF('Detalle filtrable'!$A:$A,$A15) -> 2 | D15: =COUNTIFS('Detalle filtrable'!$A:$A,$A15,'Detalle filtrable'!$C:$C,"CRÍTICA") -> 1 | E15: =COUNTIFS('Detalle filtrable'!$A:$A,$A15,'Detalle filtrable'!$C:$C,"ALTA") -> 1 | F15: yuli.verjan@quick.com.co
A16: Terrestre (por adjudicar) | B16: Terrestre SPIA→Bogotá | C16: =COUNTIF('Detalle filtrable'!$A:$A,$A16) -> 2 | D16: =COUNTIFS('Detalle filtrable'!$A:$A,$A16,'Detalle filtrable'!$C:$C,"CRÍTICA") -> 0 | E16: =COUNTIFS('Detalle filtrable'!$A:$A,$A16,'Detalle filtrable'!$C:$C,"ALTA") -> 2 | F16: Logysteel / Humadea / Quick
... A25: Vértice Seguros | B25: Seguro | C25: =COUNTIF('Detalle filtrable'!$A:$A,$A25) -> 1 | D25: =COUNTIFS('Detalle filtrable'!$A:$A,$A25,'Detalle filtrable'!$C:$C,"CRÍTICA") -> 1 | E25: =COUNTIFS('Detalle filtrable'!$A:$A,$A25,'Detalle filtrable'!$C:$C,"ALTA") -> 0 | F25: Daniel Rodríguez, Janneth Rincón (driana.cruz@ REBOTA)

Sheet Detalle filtrable
A1: DETALLE FILTRABLE — una fila por operación × proveedor · 22-jul-2026
A2: Filtra por la columna 'Proveedor' para ver todas tus operaciones activas con ese aliado y qué está pendiente con cada uno. Una operación aparece en varias filas si involucra a varios proveedores.
A4: Proveedor | B4: Rol | C4: Urgencia | D4: QT / Ref | E4: Cliente | F4: Modalidad / Ruta | G4: Etapa actual | H4: Pendiente con ESTE proveedor | I4: Referencia (DO/BL/Job) | J4: Últ. act.
A5: Aduana (por definir) | B5: Aduana | C5: ALTA | D5: QT-25192 | E5: Papagayo es Color | F5: Impo LCL · Nhava Sheva (India)→Buenaventura | G5: En tránsito; ETA 27/07; alistamiento documental | H5: Asignar la agencia de aduanas y radicar la instrucción esta semana | I5: — | J5: 14-jul
A6: Agente origen (Great Ally) | B6: Agente origen | C6: MEDIA | D6: QT-25353 | E6: INSEC Agropecuaria | F6: Impo FCL 1x20 · Shanghái→Buenaventura | G6: Prealerta; ETA primeros días de agosto | H6: Certificación de fletes y documentos originales / certificado de origen | I6: — | J6: 16-jul
A7: Aggio | B7: Flete origen | C7: ALTA | D7: QT-25265 | E7: Internacional de Eléctricos | F7: Impo FCL 1x20 + OTM · Ningbo→Buenaventura | G7: Cambio a nacionalización EN PUERTO; BL liberado; crédito $50M ok | H7: Flete pagado (US$5.062); sin pendiente de pago | I7: HBL AGLE2605497 · Ref 2605182201 | J7: 21-jul
A8: Aggio | B8: Flete origen | C8: ALTA | D8: QT-25266 | E8: Megalac (IMP088) | F8: Impo FCL 2x40 · Qingdao→Buenaventura→Zipaquirá | G8: Disputa de factura encaminada; falta liberar BL + factura de flete + DIM | H8: Definir/confirmar el pago del flete | I8: MBL 270128569 · HBL AGLE2605472 | J8: 21-jul
A9: Aggio | B9: Flete origen | C9: ALTA | D9: QT-25284 | E9: Megalac (IMP089) | F9: Impo FCL 2x40 · Qingdao→Buenaventura | G9: Arribada 15/07; radicada en Muisca; sin liberar BLs | H9: HBL telex liberado; fijar el calendario de pago del flete | I9: MBL 271637946 · HBL AGLE2606164 | J9: 17-jul
A10: Aggio | B10: Saldo MBL origen | C10: ALTA | D10: QT-25286 | E10: Velma (OTM a ZF Bogotá) | F10: Impo FCL + OTM · Ningbo→Buenaventura→ZF Bogotá | G10: Arribó ~17/07; OTM reservado; falta emisión MBL y pago anticipo | H10: Confirmar el pago del saldo del MBL (USD 6.462) | I10: HBL AGLE2606315 | J10: 22-jul
A11: Aintercarga | B11: Depósito aéreo | C11: ALTA | D11: QT-25278 | E11: XP-PEN | F11: Impo aérea · Shenzhen (vía LHR)→Bogotá | G11: LEVANTE 15/07; falta pago del cliente y entrega | H11: Pagar el bodegaje (Factura 94407, $672.219) para autorizar la salida | I11: Planilla 1178 | J11: 17-jul
A12: Andes (AndesbyApex) | B12: Flete / agente origen | C12: CRÍTICA | D12: QT-25363 | E12: Fatexcol (Mundra) | F12: Impo FCL 40HC · Mundra (India)→Buenaventura | G12: ARRIBÓ 21/07; anticipada rechazada → OTM + Zona Franca del Pacífico | H12: Pagar el flete (cotización 157521) y que liberen el MBL en destino | I12: MBL MEDUJ7873147 · Cont. TRHU7721857 | J12: 22-jul
A13: Andes (AndesbyApex) | B13: Flete / agente origen | C13: MEDIA | D13: SMDE00360861 | E13: Fatexcol (Mundra 2) | F13: Impo FCL 40HC · Mundra (India)→Buenaventura | G13: En tránsito; ETA 16-ago; HBL sin aprobar | H13: Aprobar el borrador de HBL TL/HBL/082149 y programar el pago (cotización 157687) | I13: MBL 271650171 | J13: 07-jul
A14: Anker | B14: Flete / consolidación | C14: CRÍTICA | D14: QT-24948 | E14: Hass Oil Company | F14: Expo LCL · Cartagena→Valencia (España) | G14: Booking rolado; carga en puerto CTG, nueva reserva zarpe 06-ago | H14: Cierre documental 28/07; factura Anker ~$851.916 por pagar | I14: HBL SEB-01233-2026 | J14: 22-jul
A15: Anker | B15: Flete (LCL) / cartera | C15: CRÍTICA | D15: QT-25209 | E15: Vertical Tech (1ª op) | F15: Impo LCL · Qingdao→Buenaventura | G15: Frenada +7 semanas; riesgo de ABANDONO; se destraba por HAPO | H15: Factura SIJ-01540 VENCIDA (04-jun) — programar pago; confirmar agencia autorizada | I15: Job SIJ-01540-2026 · HBL QDWJ260409638 | J15: 21-jul
... A70: Vértice Seguros | B70: Seguro | C70: CRÍTICA | D70: QT-25351 | E70: Letto (4º contenedor) | F70: Expo FCL · Cartagena→St. Vincent | G70: Perdió el corte del 20/07; SAE+selectividad enviadas; espera motonave | H70: Confirmar el amparo de la carga antes del zarpe (viajaría sin póliza) | I70: Cert. por confirmar | J70: 21-jul
